{
  "kind": "collectionType",
  "collectionName": "places_homes",
  "info": {
    "singularName": "places-home",
    "pluralName": "places-homes",
    "displayName": "PlacesHome",
    "description": ""
  },
  "options": {
    "draftAndPublish": true
  },
  "pluginOptions": {},
  "attributes": {
    "previewSection": {
      "type": "component",
      "repeatable": false,
      "component": "sections.preview"
    },
    "meetings": {
      "type": "component",
      "repeatable": false,
      "component": "sections.meetings"
    },
    "place_id": {
      "type": "string"
    },
    "hero": {
      "type": "component",
      "repeatable": false,
      "component": "hero.hero-with-slider"
    }
  }
}
